pypaypal/__init__.py
pypaypal/errors.py
pypaypal/http.py
pypaypal/clients/__init__.py
pypaypal/clients/base.py
pypaypal/clients/disputes.py
pypaypal/clients/invoicing.py
pypaypal/clients/orders.py
pypaypal/clients/payouts.py
pypaypal/clients/products.py
pypaypal/clients/rpayouts.py
pypaypal/clients/sync.py
pypaypal/clients/trackers.py
pypaypal/clients/webexp.py
pypaypal/clients/webhooks.py
pypaypal/clients/payments/__init__.py
pypaypal/clients/payments/authorizations.py
pypaypal/clients/payments/captures.py
pypaypal/clients/payments/refunds.py
pypaypal/clients/subscriptions/__init__.py
pypaypal/clients/subscriptions/plans.py
pypaypal/clients/subscriptions/subscriptions.py
pypaypal/entities/__init__.py
pypaypal/entities/base.py
pypaypal/entities/dispute.py
pypaypal/entities/orders.py
pypaypal/entities/payouts.py
pypaypal/entities/product.py
pypaypal/entities/rpayouts.py
pypaypal/entities/sync.py
pypaypal/entities/trackers.py
pypaypal/entities/webexp.py
pypaypal/entities/webhooks.py
pypaypal/entities/invoicing/__init__.py
pypaypal/entities/invoicing/invoice.py
pypaypal/entities/invoicing/template.py
pypaypal/entities/payments/__init__.py
pypaypal/entities/payments/authorizations.py
pypaypal/entities/payments/captures.py
pypaypal/entities/payments/commons.py
pypaypal/entities/payments/refunds.py
pypaypal/entities/subscriptions/__init__.py
pypaypal/entities/subscriptions/common.py
pypaypal/entities/subscriptions/plans.py
pypaypal/entities/subscriptions/subscriptions.py
pypaypal-1.0.0.dist-info/METADATA
pypaypal-1.0.0.dist-info/RECORD
pypaypal-1.0.0.dist-info/WHEEL
pypaypal-1.0.0.dist-info/top_level.txt
