Metadata-Version: 2.1
Name: pypaypal
Version: 1.0.0
Summary: Paypal API integration supporting some v1 & most of the current v2 rest APIs calls
Home-page: https://github.com/ivcuello/pypaypal
Author: ivcuello
Author-email: ivcuello@gmail.com
License: Apache License 2.0
Platform: UNKNOWN
Classifier: License :: OSI Approved :: Apache Software License
Classifier: Programming Language :: Python :: 3
Classifier: Programming Language :: Python :: 3.6
Requires-Python: >=3.6
Requires-Dist: python-dateutil
Requires-Dist: requests
